requests_file.py
requests_file-2.0.0.dist-info/LICENSE
requests_file-2.0.0.dist-info/METADATA
requests_file-2.0.0.dist-info/WHEEL
requests_file-2.0.0.dist-info/top_level.txt
requests_file-2.0.0.dist-info/RECORD
