Metadata-Version: 2.1
Name: requests-file
Version: 2.0.0
Summary: File transport adapter for Requests
Author-email: David Shea <reallylongword@gmail.com>
License: Apache 2.0
Project-URL: Homepage, https://github.com/dashea/requests-file
Classifier: Development Status :: 3 - Alpha
Classifier: Environment :: Plugins
Classifier: Intended Audience :: Developers
Classifier: License :: OSI Approved :: Apache Software License
Classifier: Programming Language :: Python :: 3
License-File: LICENSE
Requires-Dist: requests>=1.0.0
